odoo10_addon_invoice_comment_template-10.0.1.1.0-py2.7-nspkg.pth
odoo/addons/invoice_comment_template/README.rst
odoo/addons/invoice_comment_template/__init__.py
odoo/addons/invoice_comment_template/__manifest__.py
odoo/addons/invoice_comment_template/i18n/ar.po
odoo/addons/invoice_comment_template/i18n/bg.po
odoo/addons/invoice_comment_template/i18n/bs.po
odoo/addons/invoice_comment_template/i18n/ca.po
odoo/addons/invoice_comment_template/i18n/cs.po
odoo/addons/invoice_comment_template/i18n/de.po
odoo/addons/invoice_comment_template/i18n/el_GR.po
odoo/addons/invoice_comment_template/i18n/en_GB.po
odoo/addons/invoice_comment_template/i18n/es.po
odoo/addons/invoice_comment_template/i18n/es_CR.po
odoo/addons/invoice_comment_template/i18n/es_EC.po
odoo/addons/invoice_comment_template/i18n/es_MX.po
odoo/addons/invoice_comment_template/i18n/et.po
odoo/addons/invoice_comment_template/i18n/fi.po
odoo/addons/invoice_comment_template/i18n/fr.po
odoo/addons/invoice_comment_template/i18n/fr_CA.po
odoo/addons/invoice_comment_template/i18n/fr_CH.po
odoo/addons/invoice_comment_template/i18n/fr_FR.po
odoo/addons/invoice_comment_template/i18n/gl.po
odoo/addons/invoice_comment_template/i18n/hr.po
odoo/addons/invoice_comment_template/i18n/hr_HR.po
odoo/addons/invoice_comment_template/i18n/hu.po
odoo/addons/invoice_comment_template/i18n/id.po
odoo/addons/invoice_comment_template/i18n/it.po
odoo/addons/invoice_comment_template/i18n/ja.po
odoo/addons/invoice_comment_template/i18n/lt.po
odoo/addons/invoice_comment_template/i18n/mk.po
odoo/addons/invoice_comment_template/i18n/mn.po
odoo/addons/invoice_comment_template/i18n/nb.po
odoo/addons/invoice_comment_template/i18n/nb_NO.po
odoo/addons/invoice_comment_template/i18n/nl.po
odoo/addons/invoice_comment_template/i18n/nl_BE.po
odoo/addons/invoice_comment_template/i18n/nl_NL.po
odoo/addons/invoice_comment_template/i18n/pl.po
odoo/addons/invoice_comment_template/i18n/pt.po
odoo10_addon_invoice_comment_template-10.0.1.1.0.dist-info/DESCRIPTION.rst
odoo10_addon_invoice_comment_template-10.0.1.1.0.dist-info/METADATA
odoo10_addon_invoice_comment_template-10.0.1.1.0.dist-info/RECORD
odoo10_addon_invoice_comment_template-10.0.1.1.0.dist-info/WHEEL
odoo10_addon_invoice_comment_template-10.0.1.1.0.dist-info/metadata.json
odoo10_addon_invoice_comment_template-10.0.1.1.0.dist-info/namespace_packages.txt
odoo10_addon_invoice_comment_template-10.0.1.1.0.dist-info/top_level.txt
